jina_segmenter/__init__.py
jina_segmenter/segmenter.py
tests/__init__.py
tests/test_segmenter.py
jina_segmenter-0.1.0.dist-info/METADATA
jina_segmenter-0.1.0.dist-info/WHEEL
jina_segmenter-0.1.0.dist-info/top_level.txt
jina_segmenter-0.1.0.dist-info/RECORD
