Metadata-Version: 2.1
Name: jina-segmenter
Version: 0.1.0
Summary: A text segmentation tool using Jina AI API
Home-page: https://github.com/wsy/jina-segmenter
Author: WSY
Author-email: wangshuyue@gmail.com
Project-URL: Bug Tracker, https://github.com/wsy/jina-segmenter/issues
Keywords: jina,text segmentation,nlp,ai
Classifier: Development Status :: 4 - Beta
Classifier: Intended Audience :: Developers
Classifier: Topic :: Text Processing :: General
Classifier: Programming Language :: Python :: 3
Classifier: Programming Language :: Python :: 3.6
Classifier: Programming Language :: Python :: 3.7
Classifier: Programming Language :: Python :: 3.8
Classifier: Programming Language :: Python :: 3.9
Classifier: Programming Language :: Python :: 3.10
Classifier: Programming Language :: Python :: 3.11
Classifier: Programming Language :: Python :: 3.12
Classifier: License :: OSI Approved :: MIT License
Classifier: Operating System :: OS Independent
Requires-Python: >=3.6
Requires-Dist: requests>=2.31.0
